{
  "Envio CAD2003 - schema_1-0" : {
    "transaction" : "Envio CAD2003 - schema_1-0",
    "sampleCount" : 1,
    "errorCount" : 0,
    "errorPct" : 0.0,
    "meanResTime" : 3.0,
    "medianResTime" : 3.0,
    "minResTime" : 3.0,
    "maxResTime" : 3.0,
    "pct1ResTime" : 3.0,
    "pct2ResTime" : 3.0,
    "pct3ResTime" : 3.0,
    "throughput" : 333.3333333333333,
    "receivedKBytesPerSec" : 529.6223958333334,
    "sentKBytesPerSec" : 0.0
  },
  "Controller Envios - Thread  1 - schema_1" : {
    "transaction" : "Controller Envios - Thread  1 - schema_1",
    "sampleCount" : 1,
    "errorCount" : 0,
    "errorPct" : 0.0,
    "meanResTime" : 1174.0,
    "medianResTime" : 1174.0,
    "minResTime" : 1174.0,
    "maxResTime" : 1174.0,
    "pct1ResTime" : 1174.0,
    "pct2ResTime" : 1174.0,
    "pct3ResTime" : 1174.0,
    "throughput" : 0.8517887563884157,
    "receivedKBytesPerSec" : 2.364046528960818,
    "sentKBytesPerSec" : 0.9441213266609881
  },
  "Controller Envios - Thread  2 - schema_2" : {
    "transaction" : "Controller Envios - Thread  2 - schema_2",
    "sampleCount" : 1,
    "errorCount" : 0,
    "errorPct" : 0.0,
    "meanResTime" : 761.0,
    "medianResTime" : 761.0,
    "minResTime" : 761.0,
    "maxResTime" : 761.0,
    "pct1ResTime" : 761.0,
    "pct2ResTime" : 761.0,
    "pct3ResTime" : 761.0,
    "throughput" : 1.314060446780552,
    "receivedKBytesPerSec" : 3.647031044678055,
    "sentKBytesPerSec" : 1.4603523324572931
  },
  "Controller Consultas  CAD2003 - schema_2" : {
    "transaction" : "Controller Consultas  CAD2003 - schema_2",
    "sampleCount" : 2,
    "errorCount" : 1,
    "errorPct" : 50.0,
    "meanResTime" : 2686.5,
    "medianResTime" : 2686.5,
    "minResTime" : 195.0,
    "maxResTime" : 5178.0,
    "pct1ResTime" : 5178.0,
    "pct2ResTime" : 5178.0,
    "pct3ResTime" : 5178.0,
    "throughput" : 0.17688157778367383,
    "receivedKBytesPerSec" : 0.3728504742637304,
    "sentKBytesPerSec" : 0.17040398094100997
  },
  "Consulta PAR2101 schema_3" : {
    "transaction" : "Consulta PAR2101 schema_3",
    "sampleCount" : 1,
    "errorCount" : 1,
    "errorPct" : 100.0,
    "meanResTime" : 283.0,
    "medianResTime" : 283.0,
    "minResTime" : 283.0,
    "maxResTime" : 283.0,
    "pct1ResTime" : 283.0,
    "pct2ResTime" : 283.0,
    "pct3ResTime" : 283.0,
    "throughput" : 3.5335689045936394,
    "receivedKBytesPerSec" : 10.473028931095408,
    "sentKBytesPerSec" : 3.3127208480565375
  },
  "Envio CAD2003 - schema_3" : {
    "transaction" : "Envio CAD2003 - schema_3",
    "sampleCount" : 1,
    "errorCount" : 0,
    "errorPct" : 0.0,
    "meanResTime" : 308.0,
    "medianResTime" : 308.0,
    "minResTime" : 308.0,
    "maxResTime" : 308.0,
    "pct1ResTime" : 308.0,
    "pct2ResTime" : 308.0,
    "pct3ResTime" : 308.0,
    "throughput" : 3.246753246753247,
    "receivedKBytesPerSec" : 9.011008522727273,
    "sentKBytesPerSec" : 3.579672280844156
  },
  "Consulta PAR2101 schema_2" : {
    "transaction" : "Consulta PAR2101 schema_2",
    "sampleCount" : 2,
    "errorCount" : 1,
    "errorPct" : 50.0,
    "meanResTime" : 185.0,
    "medianResTime" : 185.0,
    "minResTime" : 175.0,
    "maxResTime" : 195.0,
    "pct1ResTime" : 195.0,
    "pct2ResTime" : 195.0,
    "pct3ResTime" : 195.0,
    "throughput" : 0.31730921783277805,
    "receivedKBytesPerSec" : 0.6688593229414564,
    "sentKBytesPerSec" : 0.3056890072187847
  },
  "Controller Consultas  CAD2003 - schema_3" : {
    "transaction" : "Controller Consultas  CAD2003 - schema_3",
    "sampleCount" : 1,
    "errorCount" : 1,
    "errorPct" : 100.0,
    "meanResTime" : 5288.0,
    "medianResTime" : 5288.0,
    "minResTime" : 5288.0,
    "maxResTime" : 5288.0,
    "pct1ResTime" : 5288.0,
    "pct2ResTime" : 5288.0,
    "pct3ResTime" : 5288.0,
    "throughput" : 0.18910741301059003,
    "receivedKBytesPerSec" : 0.5604892563350983,
    "sentKBytesPerSec" : 0.17728819969742812
  },
  "Envio CAD2003 - schema_2" : {
    "transaction" : "Envio CAD2003 - schema_2",
    "sampleCount" : 1,
    "errorCount" : 0,
    "errorPct" : 0.0,
    "meanResTime" : 761.0,
    "medianResTime" : 761.0,
    "minResTime" : 761.0,
    "maxResTime" : 761.0,
    "pct1ResTime" : 761.0,
    "pct2ResTime" : 761.0,
    "pct3ResTime" : 761.0,
    "throughput" : 1.314060446780552,
    "receivedKBytesPerSec" : 3.647031044678055,
    "sentKBytesPerSec" : 1.4603523324572931
  },
  "Consulta PAR2101 schema_1" : {
    "transaction" : "Consulta PAR2101 schema_1",
    "sampleCount" : 1,
    "errorCount" : 1,
    "errorPct" : 100.0,
    "meanResTime" : 254.0,
    "medianResTime" : 254.0,
    "minResTime" : 254.0,
    "maxResTime" : 254.0,
    "pct1ResTime" : 254.0,
    "pct2ResTime" : 254.0,
    "pct3ResTime" : 254.0,
    "throughput" : 3.937007874015748,
    "receivedKBytesPerSec" : 11.66876845472441,
    "sentKBytesPerSec" : 3.690944881889764
  },
  "Envio CAD2003 - schema_1" : {
    "transaction" : "Envio CAD2003 - schema_1",
    "sampleCount" : 1,
    "errorCount" : 0,
    "errorPct" : 0.0,
    "meanResTime" : 1174.0,
    "medianResTime" : 1174.0,
    "minResTime" : 1174.0,
    "maxResTime" : 1174.0,
    "pct1ResTime" : 1174.0,
    "pct2ResTime" : 1174.0,
    "pct3ResTime" : 1174.0,
    "throughput" : 0.8517887563884157,
    "receivedKBytesPerSec" : 2.364046528960818,
    "sentKBytesPerSec" : 0.9441213266609881
  },
  "Controller Consultas  CAD2003 - schema_1" : {
    "transaction" : "Controller Consultas  CAD2003 - schema_1",
    "sampleCount" : 1,
    "errorCount" : 1,
    "errorPct" : 100.0,
    "meanResTime" : 5259.0,
    "medianResTime" : 5259.0,
    "minResTime" : 5259.0,
    "maxResTime" : 5259.0,
    "pct1ResTime" : 5259.0,
    "pct2ResTime" : 5259.0,
    "pct3ResTime" : 5259.0,
    "throughput" : 0.19015021867275148,
    "receivedKBytesPerSec" : 0.5635799938201178,
    "sentKBytesPerSec" : 0.1782658300057045
  },
  "Total" : {
    "transaction" : "Total",
    "sampleCount" : 13,
    "errorCount" : 6,
    "errorPct" : 46.153847,
    "meanResTime" : 1452.3846153846152,
    "medianResTime" : 283.0,
    "minResTime" : 0.0,
    "maxResTime" : 5288.0,
    "pct1ResTime" : 5276.4,
    "pct2ResTime" : 5288.0,
    "pct3ResTime" : 5288.0,
    "throughput" : 1.0380899145572147,
    "receivedKBytesPerSec" : 2.5655138295536215,
    "sentKBytesPerSec" : 0.7975949253373792
  },
  "Controller Envios - Thread  3 - schema_3" : {
    "transaction" : "Controller Envios - Thread  3 - schema_3",
    "sampleCount" : 1,
    "errorCount" : 0,
    "errorPct" : 0.0,
    "meanResTime" : 308.0,
    "medianResTime" : 308.0,
    "minResTime" : 308.0,
    "maxResTime" : 308.0,
    "pct1ResTime" : 308.0,
    "pct2ResTime" : 308.0,
    "pct3ResTime" : 308.0,
    "throughput" : 3.246753246753247,
    "receivedKBytesPerSec" : 9.011008522727273,
    "sentKBytesPerSec" : 3.579672280844156
  },
  "Envio CAD2003 - schema_3-0" : {
    "transaction" : "Envio CAD2003 - schema_3-0",
    "sampleCount" : 1,
    "errorCount" : 0,
    "errorPct" : 0.0,
    "meanResTime" : 0.0,
    "medianResTime" : 0.0,
    "minResTime" : 0.0,
    "maxResTime" : 0.0,
    "pct1ResTime" : 0.0,
    "pct2ResTime" : 0.0,
    "pct3ResTime" : 0.0,
    "throughput" : "Infinity",
    "receivedKBytesPerSec" : "Infinity",
    "sentKBytesPerSec" : "NaN"
  },
  "Envio CAD2003 - schema_2-0" : {
    "transaction" : "Envio CAD2003 - schema_2-0",
    "sampleCount" : 1,
    "errorCount" : 0,
    "errorPct" : 0.0,
    "meanResTime" : 3.0,
    "medianResTime" : 3.0,
    "minResTime" : 3.0,
    "maxResTime" : 3.0,
    "pct1ResTime" : 3.0,
    "pct2ResTime" : 3.0,
    "pct3ResTime" : 3.0,
    "throughput" : 333.3333333333333,
    "receivedKBytesPerSec" : 529.6223958333334,
    "sentKBytesPerSec" : 0.0
  }
}